LICENSE
MANIFEST.in
README.md
pavement.py
setup.py
hardDecisions/__init__.py
hardDecisions/decisiontree.py
hardDecisions/demo.py
hardDecisions/precisiontree.py
hardDecisions/supertree.py
hardDecisions/treenode.py
hardDecisions/treeplan.py
hardDecisions/x-decisiontree.py
hardDecisions.egg-info/PKG-INFO
hardDecisions.egg-info/SOURCES.txt
hardDecisions.egg-info/dependency_links.txt
hardDecisions.egg-info/not-zip-safe
hardDecisions.egg-info/top_level.txt