Metadata-Version: 1.1
Name: hardDecisions
Version: 0.0.2
Summary: Decision making tree modeling using Python
Home-page: http://github.com/jdvelasq/hardDecisions
Author: Juan D. Velasquez & Ibeth K. Vergara
Author-email: jdvelasq@unal.edu.co
License: MIT
Keywords: decision-tree decision-making operations-research analytics
Platform: UNKNOWN
Classifier: Development Status :: 3 - Alpha
Classifier: License :: OSI Approved :: MIT License
Classifier: Programming Language :: Python :: 3.5
Classifier: Topic :: Office/Business :: Financial
